{"title":"dexs-ui 界面优化调整","features":["深浅色模式Logo自适应显示","钱包选择器按钮高度统一","首页统计网格透明度优化","底部栏位重构为功能导航布局","路由功能实现","错误修复和代码优化"],"tech":{"Web":{"arch":"react","component":"radix-ui + tailwind"}},"design":"保持现有设计风格，重点优化用户体验：1. Logo根据主题模式自动切换颜色 2. 统一界面元素高度提升视觉一致性 3. 增强浅色模式下内容可读性 4. 重构底部为信息丰富的导航区域 5. 实现页面导航功能 6. 修复所有编译错误和警告","plan":{"step1_logo_adaptation":"done","step2_button_height_unify":"done","step3_grid_opacity_enhance":"done","step4_footer_restructure":"done","step5_routing_implementation":"done","step6_error_fixes":"done","step7_final_optimization":"done"}}